autora/experiment_runner/synthetic/psychology/ssm/__init__.py
autora/experiment_runner/synthetic/psychology/ssm/_lmm.py
autora_experiment_runner_synthetic_psychology_ssm-0.0.2.dist-info/LICENSE
autora_experiment_runner_synthetic_psychology_ssm-0.0.2.dist-info/METADATA
autora_experiment_runner_synthetic_psychology_ssm-0.0.2.dist-info/WHEEL
autora_experiment_runner_synthetic_psychology_ssm-0.0.2.dist-info/top_level.txt
autora_experiment_runner_synthetic_psychology_ssm-0.0.2.dist-info/RECORD
