Metadata-Version: 2.1
Name: autora-experiment-runner-synthetic-psychology-ssm
Version: 0.0.2
Summary: Run synthetic experiments with hierarchical sequential sampling models
Author-email: Younes Strittamtter <younes_strittmatter@brown.edu>
License: Copyright (c) 2023 Enter your full name
Project-URL: homepage, http://www.empiricalresearch.ai
Project-URL: repository, https://github.com/AutoResearch/autora-synthetic-psychology-ssm
Project-URL: documentation, https://autoresearch.github.io/autora/
Requires-Python: <4,>=3.8
License-File: LICENSE
Requires-Dist: autora-core
Requires-Dist: autora-synthetic
Requires-Dist: ssm-simulators ==0.5.3
Provides-Extra: dev
Requires-Dist: autora-core[dev] ; extra == 'dev'
